echostream_terrafy/__init__.py
echostream_terrafy/__main__.py
echostream_terrafy/data_sources.py
echostream_terrafy/objects.py
echostream_terrafy/resources.py
echostream_terrafy-0.0.12.dist-info/LICENSE
echostream_terrafy-0.0.12.dist-info/METADATA
echostream_terrafy-0.0.12.dist-info/WHEEL
echostream_terrafy-0.0.12.dist-info/entry_points.txt
echostream_terrafy-0.0.12.dist-info/top_level.txt
echostream_terrafy-0.0.12.dist-info/RECORD
