Metadata-Version: 2.2
Name: echostream-terrafy
Version: 0.0.12
Summary: Takes an existing EchoStream Tenant and creates a Terraform script and statefile for it
Home-page: https://github.com/Echo-Stream/echostream-terrafy
Author: EchoStream
Author-email: support@echo.stream
License: Apache License 2.0
Project-URL: Bug Tracker, https://github.com/Echo-Stream/echostream-terrafy/issues
Project-URL: Source Code, https://github.com/Echo-Stream/echostream-terrafy
Keywords: echostream,terraform,opentofu,tofu,terrafy
Platform: posix
Classifier: License :: OSI Approved :: Apache Software License
Classifier: Operating System :: POSIX
Classifier: Operating System :: POSIX :: Linux
Classifier: Operating System :: MacOS :: MacOS X
Classifier: Programming Language :: Python :: 3
Classifier: Programming Language :: Python :: 3.9
Classifier: Programming Language :: Python :: 3.10
Classifier: Programming Language :: Python :: 3.11
Classifier: Programming Language :: Python :: 3.12
Classifier: Programming Language :: Python :: 3.13
Requires-Python: >=3.9
License-File: LICENSE
Requires-Dist: argh==0.31.3
Requires-Dist: deepmerge==2.0
Requires-Dist: gql[requests]==3.5.0
Requires-Dist: pycognito==2022.12.0
Requires-Dist: simplejson==3.19.3
Requires-Dist: termcolor==2.5.0
